vmath.cp36-win_amd64.pyd
vmath-0.3.0.data/data/vmath.pyi
vmath-0.3.0.dist-info/LICENSE
vmath-0.3.0.dist-info/METADATA
vmath-0.3.0.dist-info/WHEEL
vmath-0.3.0.dist-info/top_level.txt
vmath-0.3.0.dist-info/RECORD
